{
   "@context": {
      "iata": "https://onerecord.iata.org/"
   },
   "@type": "iata:BookingSegment",
   "iata:bookingSegment:arrivalLocation" : {
      "@id": "iata:Location/thisObjectId",
      "@type": "iata:Location"
   },
   "iata:bookingSegment:bookingOptions" : {
      "@id": "iata:BookingOption/thisObjectId",
      "@type": "iata:BookingOption"
   },
   "iata:bookingSegment:departureLocation" : {
      "@id": "iata:Location/thisObjectId",
      "@type": "iata:Location"
   },
   "iata:bookingSegment:requests" : {
      "@id": "iata:BookingOptionRequest/thisObjectId",
      "@type": "iata:BookingOptionRequest"
   },
   "iata:bookingSegment:preferredTransportId" : "string"
}