{
   "@context": {
      "iata": "https://onerecord.iata.org/"
   },
   "@type": "iata:BookingTimes",
   "iata:bookingtimes:bookingOption" : {
      "@id": "iata:BookingOption/thisObjectId",
      "@type": "iata:BookingOption"
   },
   "iata:bookingtimes:bookingOptionRequest" : {
      "@id": "iata:BookingOptionRequest/thisObjectId",
      "@type": "iata:BookingOptionRequest"
   },
   "iata:bookingtimes:earliestAcceptanceTime" : "dateTime",
   "iata:bookingtimes:latestAcceptanceTime" : "dateTime",
   "iata:bookingtimes:timeOfAvailability" : "dateTime",
   "iata:bookingtimes:totalTransitTime" : {
      "@id": "iata:xsdduration/thisObjectId",
      "@type": "iata:xsdduration"
   }
}